cutword/__init__.py
cutword/comparewithjieba.py
cutword/cutword.py
cutword/dict.txt
cutword/unionwords.txt
cutword_lite-0.2.0.dist-info/METADATA
cutword_lite-0.2.0.dist-info/WHEEL
cutword_lite-0.2.0.dist-info/top_level.txt
cutword_lite-0.2.0.dist-info/RECORD
