Metadata-Version: 2.4
Name: cutword-lite
Version: 0.2.0
Summary: Just Cut Word Faster
Home-page: https://github.com/basicv8vc/cutword-lite
Author: basicv8vc
License: Apache License 2.0
Requires-Python: >=3
Requires-Dist: numpy
Requires-Dist: pyahocorasick
Dynamic: author
Dynamic: description
Dynamic: description-content-type
Dynamic: home-page
Dynamic: license
Dynamic: requires-dist
Dynamic: requires-python
Dynamic: summary
